src/google_api_xpandapaws/Google.py
src/google_api_xpandapaws/__init__.py
cloud_google_api_v1_0_1-1.0.1.dist-info/METADATA
cloud_google_api_v1_0_1-1.0.1.dist-info/WHEEL
cloud_google_api_v1_0_1-1.0.1.dist-info/licenses/LICENSE
cloud_google_api_v1_0_1-1.0.1.dist-info/RECORD
