Metadata-Version: 2.1
Name: cloud_google_api_v1.0.1
Version: 1.0.1
Summary: Google_API_Cloud
Project-URL: Homepage, https://github.com/pypa/sampleproject
Project-URL: Bug Tracker, https://github.com/pypa/sampleproject/issues
Author-email: xPandaPaws <chevy.chan.2021@smu.edu.sg>
License-File: LICENSE
Classifier: License :: OSI Approved :: MIT License
Classifier: Operating System :: OS Independent
Classifier: Programming Language :: Python :: 3
Requires-Python: >=3.7
